setup.py
s2aiobe/__init__.py
s2aiobe/__main__.py
s2aiomulti.egg-info/PKG-INFO
s2aiomulti.egg-info/SOURCES.txt
s2aiomulti.egg-info/dependency_links.txt
s2aiomulti.egg-info/entry_points.txt
s2aiomulti.egg-info/requires.txt
s2aiomulti.egg-info/top_level.txt
s2aior/__init__.py
s2aior/__main__.py
s2aior/configuration/__init__.py
s2aior/configuration/configuration.cfg
s2aior/configuration/logo.png
s2aior/miscellaneous/errors.txt
s2aior/scratch_files/extensions/m_s2aio.s2e
s2aior/scratch_files/extensions/m_s2aio_DE.s2e
s2aior/scratch_files/extensions/m_s2aio_ES.s2e
s2aior/scratch_files/extensions/m_s2aio_FR.s2e
s2aior/scratch_files/extensions/m_s2aio_GR.s2e
s2aior/scratch_files/extensions/m_s2aio_IT.s2e
s2aior/scratch_files/extensions/m_s2aio_KO.s2e
s2aior/scratch_files/extensions/m_s2aio_NL.s2e
s2aior/scratch_files/extensions/m_s2aio_PT.s2e
s2aior/scratch_files/extensions/m_s2aio_zh_CN.s2e
s2aior/scratch_files/extensions/m_s2aio_zh_TW.s2e
s2aior/scratch_files/projects/m_s2aio.sb2
s2aior/scratch_files/projects/m_s2aio_DE.sb2
s2aior/scratch_files/projects/m_s2aio_ES.sb2
s2aior/scratch_files/projects/m_s2aio_FR.sb2
s2aior/scratch_files/projects/m_s2aio_GR.sb2
s2aior/scratch_files/projects/m_s2aio_IT.sb2
s2aior/scratch_files/projects/m_s2aio_KO.sb2
s2aior/scratch_files/projects/m_s2aio_PT.sb2
s2aior/scratch_files/projects/m_s2aio_nl.sb2
s2aior/scratch_files/projects/m_s2aio_zh_CN.sb2
s2aior/scratch_files/projects/m_s2aio_zh_TW.sb2
s2aios/__init__.py
s2aios/__main__.py