Metadata-Version: 1.1
Name: s2aiomulti
Version: 1.3
Summary: Arduino Multi-Board HTTP Controller and Router
Home-page: https://github.com/MrYsLab/s2aiomulti/wiki
Author: Alan Yorinks
Author-email: MisterYsLab@gmail.com
License: GNU General Public License v3 (GPLv3)
Download-URL: https://github.com/MrYsLab/s2aiomulti
Keywords: Firmata,Arduino,Scratch
Platform: UNKNOWN
Classifier: Development Status :: 5 - Production/Stable
Classifier: Environment :: Other Environment
Classifier: Intended Audience :: Education
Classifier: License :: OSI Approved :: GNU General Public License v3 or later (GPLv3+)
Classifier: Operating System :: OS Independent
Classifier: Programming Language :: Python :: 3.5
Classifier: Topic :: Education
